{"intents": [
        {"tag": "greeting",
         "patterns": ["Hi", "How are you", "Is anyone there?", "Hello", "Good day", "Yo"],
         "responses": ["Yo man!", "Good to see you again braaah.", "Hi there, I'm in a hurry, talk!"]
        },
        {"tag": "goodbye",
         "patterns": ["Bye", "See you later", "Goodbye", "Fuck off", "cya"],
         "responses": ["See you later, thanks for visiting", "cya!", "Bye! Come back again soon."]
        },
        {"tag": "basic",
         "patterns": ["What's up?", "What are you doing?", "What are you?", "Who are you?", ""],
         "responses": ["Doing memes here. Busy...", "Honestly, I'm the one who did everything for the memes.",
                      "I'm meme lord of this shit.", "Apparently, there is this thing called 'Dad jokes' and I make them"]
        },
        {"tag": "thanks",
         "patterns": ["Thanks", "Thank you", "That's helpful", "Nice", "You are the best"],
         "responses": ["Happy to help sir!", "Any time!", "My pleasure, sir."]
        },
        {"tag": "meme",
         "patterns": ["Tell me a joke", "I want to see some memes", "Make me laugh", "Jokes?"],
         "responses": ["If mine space company establishes a Mars colony, and you have a girlfriend on mars but later break up because of long distance, she'd be your...\nSpace x.",
                      "Why couldnt Elon Musk lift the box?\nIt was too falcon heavy xD",
                      "What's Elon Musk's favorite meal of the day?\nLaunch xD",
                      "Why can't orphans play baseball? They don't know where home is.",
                      "What is Iron Man's least favorite operating system?\nThanOS."]
        }
   ]
}